dockwatch/__init__.py
dockwatch/analyzer.py
dockwatch/cli.py
dockwatch/creator.py
dockwatch/image_analyzer.py
dockwatch/monitor.py
dockwatch-1.0.dist-info/licenses/LICENSE
dockwatch-1.0.dist-info/METADATA
dockwatch-1.0.dist-info/WHEEL
dockwatch-1.0.dist-info/entry_points.txt
dockwatch-1.0.dist-info/top_level.txt
dockwatch-1.0.dist-info/RECORD
