Metadata-Version: 2.4
Name: dockwatch
Version: 1.0
Summary: 🛡️  DockWatch - Docker container monitoring and image analysis cli tool.
Author: Saimon Bhuiyan
Author-email: Saimon Bhuiyan <bsse1402@iit.du.ac.bd>
Requires-Python: >=3.7
License-File: LICENSE
Requires-Dist: docker
Requires-Dist: rich
Dynamic: author
Dynamic: license-file
Dynamic: requires-python
